mlboardclient/__init__.py
mlboardclient/exceptions.py
mlboardclient/tf_conf.py
mlboardclient/utils.py
mlboardclient/api/__init__.py
mlboardclient/api/base.py
mlboardclient/api/client.py
mlboardclient/api/context.py
mlboardclient/api/httpclient.py
mlboardclient/api/v2/__init__.py
mlboardclient/api/v2/apps.py
mlboardclient/api/v2/client.py
mlboardclient/api/v2/datasets.py
mlboardclient/api/v2/executor.py
mlboardclient/api/v2/keys.py
mlboardclient/api/v2/optimizator.py
mlboardclient/api/v2/servings.py
mlboardclient/api/v2/tasks.py
mlboardclient/ml_serving_utils/__init__.py
mlboardclient/ml_serving_utils/compat.py
mlboardclient/ml_serving_utils/dtypes.py
mlboardclient/ml_serving_utils/helpers.py
mlboardclient/ml_serving_utils/predict_pb2.py
mlboardclient/ml_serving_utils/predict_pb2_grpc.py
mlboardclient/ml_serving_utils/resource_handle_pb2.py
mlboardclient/ml_serving_utils/tensor_pb2.py
mlboardclient/ml_serving_utils/tensor_shape.py
mlboardclient/ml_serving_utils/tensor_shape_pb2.py
mlboardclient/ml_serving_utils/tensor_util.py
mlboardclient/ml_serving_utils/types_pb2.py
mlboardclient/report/tensorflow_rpt.py
mlboardclient/report/tensorlogs.py
mlboardclient/tests/__init__.py
python_mlboardclient-1.2.0.dist-info/AUTHORS
python_mlboardclient-1.2.0.dist-info/METADATA
python_mlboardclient-1.2.0.dist-info/WHEEL
python_mlboardclient-1.2.0.dist-info/entry_points.txt
python_mlboardclient-1.2.0.dist-info/pbr.json
python_mlboardclient-1.2.0.dist-info/top_level.txt
python_mlboardclient-1.2.0.dist-info/RECORD
