Metadata-Version: 2.1
Name: python-mlboardclient
Version: 1.2.0
Summary: Ml-Board Client Library
Home-page: UNKNOWN
Author: KuberLab
License: Apache Software License
Platform: UNKNOWN
Classifier: Programming Language :: Python
Classifier: Programming Language :: Python :: 2
Classifier: Programming Language :: Python :: 2.7
Classifier: Programming Language :: Python :: 3
Classifier: Programming Language :: Python :: 3.5
Classifier: Intended Audience :: Information Technology
Classifier: Intended Audience :: System Administrators
Classifier: License :: OSI Approved :: Apache Software License
Classifier: Operating System :: POSIX :: Linux
Requires-Dist: pbr (!=2.1.0,>=2.0.0)
Requires-Dist: PyYAML (>=3.10.0)
Requires-Dist: requests (>=2.14.2)
Requires-Dist: six (>=1.9.0)
Requires-Dist: eventlet
Requires-Dist: bayesian-optimization
Requires-Dist: scikit-optimize
Requires-Dist: grpcio (>=1.17.1)
Requires-Dist: grpcio-tools (>=1.17.1)
Requires-Dist: subprocess32 ; (python_version < '3')
